[
  {
    "ID": 2994,
    "stringCommand": ":A:",
    "Command": [
      "A"
    ],
    "Stance": null,
    "HitLevel": [
      "H"
    ],
    "Impact": 18,
    "Damage": "16",
    "DamageDec": 16,
    "Block": "-6",
    "BlockDec": -6,
    "Hit": "2",
    "HitDec": 2,
    "CounterHit": "2",
    "CounterHitDec": 2,
    "GuardBurst": 1,
    "Notes": null
  },
  {
    "ID": 2995,
    "stringCommand": ":A::A:",
    "Command": [
      "A",
      "A"
    ],
    "Stance": null,
    "HitLevel": [
      "H",
      "H"
    ],
    "Impact": 18,
    "Damage": "16,12",
    "DamageDec": 28,
    "Block": "-12",
    "BlockDec": -12,
    "Hit": "0",
    "HitDec": 0,
    "CounterHit": "0",
    "CounterHitDec": 0,
    "GuardBurst": 3,
    "Notes": "NC"
  },
  {
    "ID": 2996,
    "stringCommand": ":A::A::A:",
    "Command": [
      "A",
      "A",
      "A"
    ],
    "Stance": null,
    "HitLevel": [
      "H",
      "H",
      "L"
    ],
    "Impact": 18,
    "Damage": "16,12,26",
    "DamageDec": 54,
    "Block": "-12",
    "BlockDec": -12,
    "Hit": "0",
    "HitDec": 0,
    "CounterHit": "0",
    "CounterHitDec": 0,
    "GuardBurst": 5,
    "Notes": "3rd A interruptible by i17 and jumping attacks on guard | 3rd hit never combos"
  },
  {
    "ID": 2997,
    "stringCommand": ":A::A::B:",
    "Command": [
      "A",
      "A",
      "B"
    ],
    "Stance": null,
    "HitLevel": [
      "H",
      "H",
      "M"
    ],
    "Impact": 18,
    "Damage": "16,12,30",
    "DamageDec": 58,
    "Block": "-14",
    "BlockDec": -14,
    "Hit": "KND",
    "HitDec": null,
    "CounterHit": "KND",
    "CounterHitDec": null,
    "GuardBurst": 8,
    "Notes": "NCC. Uninterruptible on guard but the B can be dodged | 3rd hit on CH gives sliding KND"
  },
  {
    "ID": 2998,
    "stringCommand": ":6::A:",
    "Command": [
      "6",
      "A"
    ],
    "Stance": null,
    "HitLevel": [
      "H"
    ],
    "Impact": 20,
    "Damage": "20",
    "DamageDec": 20,
    "Block": "-18",
    "BlockDec": -18,
    "Hit": "KND",
    "HitDec": null,
    "CounterHit": "KND",
    "CounterHitDec": null,
    "GuardBurst": 5,
    "Notes": "TC. :LH: on long range running counterhit"
  },
  {
    "ID": 2999,
    "stringCommand": ":6::A:",
    "Command": [
      "6",
      "A"
    ],
    "Stance": [
      "tip range"
    ],
    "HitLevel": [
      "H"
    ],
    "Impact": 20,
    "Damage": "32",
    "DamageDec": 32,
    "Block": "-8",
    "BlockDec": -8,
    "Hit": "KND",
    "HitDec": null,
    "CounterHit": "KND",
    "CounterHitDec": null,
    "GuardBurst": 5,
    "Notes": "TC. :LH: on long range running counterhit"
  },
  {
    "ID": 3000,
    "stringCommand": ":3::A:",
    "Command": [
      "3",
      "A"
    ],
    "Stance": null,
    "HitLevel": [
      "M"
    ],
    "Impact": 26,
    "Damage": "14",
    "DamageDec": 14,
    "Block": "-14",
    "BlockDec": -14,
    "Hit": "-6",
    "HitDec": -6,
    "CounterHit": "-6",
    "CounterHitDec": -6,
    "GuardBurst": 1,
    "Notes": "Recovers crouching"
  },
  {
    "ID": 3001,
    "stringCommand": ":3::A:",
    "Command": [
      "3",
      "A"
    ],
    "Stance": [
      "tip range"
    ],
    "HitLevel": [
      "M"
    ],
    "Impact": 26,
    "Damage": "24",
    "DamageDec": 24,
    "Block": "-4",
    "BlockDec": -4,
    "Hit": "4",
    "HitDec": 4,
    "CounterHit": "4",
    "CounterHitDec": 4,
    "GuardBurst": 3,
    "Notes": "Recovers crouching"
  },
  {
    "ID": 3002,
    "stringCommand": ":3::A::A:",
    "Command": [
      "3",
      "A",
      "A"
    ],
    "Stance": null,
    "HitLevel": [
      "M",
      "L"
    ],
    "Impact": 26,
    "Damage": "14,22",
    "DamageDec": 36,
    "Block": "-12",
    "BlockDec": -12,
    "Hit": "KND",
    "HitDec": null,
    "CounterHit": "KND",
    "CounterHitDec": null,
    "GuardBurst": 1,
    "Notes": "NCC. TC. Recovers crouching. Uninterruptible but jumpable. Delayable"
  },
  {
    "ID": 3003,
    "stringCommand": ":3::A::A:",
    "Command": [
      "3",
      "A",
      "A"
    ],
    "Stance": [
      "tip range"
    ],
    "HitLevel": [
      "M",
      "L"
    ],
    "Impact": 26,
    "Damage": "24,22",
    "DamageDec": 46,
    "Block": "-12",
    "BlockDec": -12,
    "Hit": "KND",
    "HitDec": null,
    "CounterHit": "KND",
    "CounterHitDec": null,
    "GuardBurst": 3,
    "Notes": "NCC. TC. Recovers crouching. Uninterruptible but jumpable. Delayable"
  },
  {
    "ID": 3004,
    "stringCommand": ":2::A:",
    "Command": [
      "2",
      "A"
    ],
    "Stance": null,
    "HitLevel": [
      "SL"
    ],
    "Impact": 12,
    "Damage": "12",
    "DamageDec": 12,
    "Block": "-6",
    "BlockDec": -6,
    "Hit": "2",
    "HitDec": 2,
    "CounterHit": "2",
    "CounterHitDec": 2,
    "GuardBurst": 1,
    "Notes": "Recovers crouching"
  },
  {
    "ID": 3005,
    "stringCommand": ":1::A:",
    "Command": [
      "1",
      "A"
    ],
    "Stance": null,
    "HitLevel": [
      "L"
    ],
    "Impact": 24,
    "Damage": "32",
    "DamageDec": 32,
    "Block": "-16",
    "BlockDec": -16,
    "Hit": "KND",
    "HitDec": null,
    "CounterHit": "KND",
    "CounterHitDec": null,
    "GuardBurst": 1,
    "Notes": "Gives +8 on early throw break, +2 on later. :LH: triggers after 3 BA on hit"
  },
  {
    "ID": 3006,
    "stringCommand": ":1::(A):",
    "Command": [
      "1",
      "(A)"
    ],
    "Stance": null,
    "HitLevel": [
      "L"
    ],
    "Impact": 24,
    "Damage": "47",
    "DamageDec": 47,
    "Block": "-16",
    "BlockDec": -16,
    "Hit": "KND",
    "HitDec": null,
    "CounterHit": "KND",
    "CounterHitDec": null,
    "GuardBurst": 1,
    "Notes": "Gives +8 on early throw break, +2 on later"
  },
  {
    "ID": 3007,
    "stringCommand": ":1::A:",
    "Command": [
      "1",
      "A"
    ],
    "Stance": [
      "tip range"
    ],
    "HitLevel": [
      "L"
    ],
    "Impact": 24,
    "Damage": "12",
    "DamageDec": 12,
    "Block": "-16",
    "BlockDec": -16,
    "Hit": "-4",
    "HitDec": -4,
    "CounterHit": "KND",
    "CounterHitDec": null,
    "GuardBurst": 1,
    "Notes": null
  },
  {
    "ID": 3008,
    "stringCommand": ":1::(A):",
    "Command": [
      "1",
      "(A)"
    ],
    "Stance": [
      "tip range"
    ],
    "HitLevel": [
      "L"
    ],
    "Impact": 24,
    "Damage": "12",
    "DamageDec": 12,
    "Block": "-16",
    "BlockDec": -16,
    "Hit": "-4",
    "HitDec": -4,
    "CounterHit": "KND",
    "CounterHitDec": null,
    "GuardBurst": 1,
    "Notes": null
  },
  {
    "ID": 3009,
    "stringCommand": ":4::A:",
    "Command": [
      "4",
      "A"
    ],
    "Stance": null,
    "HitLevel": [
      "L"
    ],
    "Impact": 26,
    "Damage": "14",
    "DamageDec": 14,
    "Block": "-18",
    "BlockDec": -18,
    "Hit": "-6",
    "HitDec": -6,
    "CounterHit": "-6",
    "CounterHitDec": -6,
    "GuardBurst": 1,
    "Notes": ":TS:"
  },
  {
    "ID": 3010,
    "stringCommand": ":7::A:",
    "Command": [
      "7",
      "A"
    ],
    "Stance": null,
    "HitLevel": [
      "L"
    ],
    "Impact": 36,
    "Damage": "20",
    "DamageDec": 20,
    "Block": "-15",
    "BlockDec": -15,
    "Hit": "-3",
    "HitDec": -3,
    "CounterHit": "-3",
    "CounterHitDec": -3,
    "GuardBurst": 1,
    "Notes": ":TJ[4-]"
  },
  {
    "ID": 3011,
    "stringCommand": ":8::A:",
    "Command": [
      "8",
      "A"
    ],
    "Stance": null,
    "HitLevel": [
      "L"
    ],
    "Impact": 36,
    "Damage": "24",
    "DamageDec": 24,
    "Block": "-8",
    "BlockDec": -8,
    "Hit": "KND",
    "HitDec": null,
    "CounterHit": "KND",
    "CounterHitDec": null,
    "GuardBurst": 4,
    "Notes": ":TJ[4-]"
  },
  {
    "ID": 3012,
    "stringCommand": ":2::A:",
    "Command": [
      "2",
      "A"
    ],
    "Stance": [
      "FC"
    ],
    "HitLevel": [
      "SL"
    ],
    "Impact": 12,
    "Damage": "12",
    "DamageDec": 12,
    "Block": "-6",
    "BlockDec": -6,
    "Hit": "2",
    "HitDec": 2,
    "CounterHit": "2",
    "CounterHitDec": 2,
    "GuardBurst": 1,
    "Notes": "TC[?-RC]"
  },
  {
    "ID": 3013,
    "stringCommand": ":3::A:",
    "Command": [
      "3",
      "A"
    ],
    "Stance": [
      "FC"
    ],
    "HitLevel": [
      "M"
    ],
    "Impact": 14,
    "Damage": "10",
    "DamageDec": 10,
    "Block": "-12",
    "BlockDec": -12,
    "Hit": "0",
    "HitDec": 0,
    "CounterHit": "0",
    "CounterHitDec": 0,
    "GuardBurst": 1,
    "Notes": null
  },
  {
    "ID": 3014,
    "stringCommand": ":3::A::K:",
    "Command": [
      "3",
      "A",
      "C"
    ],
    "Stance": [
      "FC"
    ],
    "HitLevel": [
      "M",
      "H"
    ],
    "Impact": 14,
    "Damage": "10,14",
    "DamageDec": 24,
    "Block": "-6",
    "BlockDec": -6,
    "Hit": "2",
    "HitDec": 2,
    "CounterHit": "2",
    "CounterHitDec": 2,
    "GuardBurst": 3,
    "Notes": "NC. Jails. KND on CH if first hit misses"
  },
  {
    "ID": 3015,
    "stringCommand": ":A:",
    "Command": [
      "A"
    ],
    "Stance": [
      "WR"
    ],
    "HitLevel": [
      "M"
    ],
    "Impact": 18,
    "Damage": "14",
    "DamageDec": 14,
    "Block": "-4",
    "BlockDec": -4,
    "Hit": "6",
    "HitDec": 6,
    "CounterHit": "6",
    "CounterHitDec": 6,
    "GuardBurst": 1,
    "Notes": "TC"
  },
  {
    "ID": 3016,
    "stringCommand": ":A::A:",
    "Command": [
      "A",
      "A"
    ],
    "Stance": [
      "WR"
    ],
    "HitLevel": [
      "M",
      "M"
    ],
    "Impact": 18,
    "Damage": "14,16",
    "DamageDec": 30,
    "Block": "-7",
    "BlockDec": -7,
    "Hit": "2",
    "HitDec": 2,
    "CounterHit": "2",
    "CounterHitDec": 2,
    "GuardBurst": 3,
    "Notes": "TC. NCC"
  },
  {
    "ID": 3017,
    "stringCommand": ":A:",
    "Command": [
      "A"
    ],
    "Stance": [
      "BT"
    ],
    "HitLevel": [
      "H"
    ],
    "Impact": 20,
    "Damage": "16",
    "DamageDec": 16,
    "Block": "-2",
    "BlockDec": -2,
    "Hit": "8",
    "HitDec": 8,
    "CounterHit": "8",
    "CounterHitDec": 8,
    "GuardBurst": 1,
    "Notes": "TC[13-RC]"
  },
  {
    "ID": 3018,
    "stringCommand": ":2::A:",
    "Command": [
      "2",
      "A"
    ],
    "Stance": [
      "BT"
    ],
    "HitLevel": [
      "SL"
    ],
    "Impact": 20,
    "Damage": "18",
    "DamageDec": 18,
    "Block": "-6",
    "BlockDec": -6,
    "Hit": "4",
    "HitDec": 4,
    "CounterHit": "4",
    "CounterHitDec": 4,
    "GuardBurst": 1,
    "Notes": null
  },
  {
    "ID": 3019,
    "stringCommand": ":B:",
    "Command": [
      "B"
    ],
    "Stance": null,
    "HitLevel": [
      "M"
    ],
    "Impact": 20,
    "Damage": "14",
    "DamageDec": 14,
    "Block": "-6",
    "BlockDec": -6,
    "Hit": "2",
    "HitDec": 2,
    "CounterHit": "2",
    "CounterHitDec": 2,
    "GuardBurst": 2,
    "Notes": "OTG"
  },
  {
    "ID": 3020,
    "stringCommand": ":B::B:",
    "Command": [
      "B",
      "B"
    ],
    "Stance": null,
    "HitLevel": [
      "M",
      "M"
    ],
    "Impact": 20,
    "Damage": "14,12",
    "DamageDec": 26,
    "Block": "-14",
    "BlockDec": -14,
    "Hit": "-6",
    "HitDec": -6,
    "CounterHit": "STN",
    "CounterHitDec": null,
    "GuardBurst": 4,
    "Notes": "NC. On guard, 2nd hit cannot be evaded but can be GId"
  },
  {
    "ID": 3021,
    "stringCommand": ":B::(B):",
    "Command": [
      "B",
      "(B)"
    ],
    "Stance": null,
    "HitLevel": [
      "M",
      "M"
    ],
    "Impact": 20,
    "Damage": "14,12",
    "DamageDec": 26,
    "Block": "-6",
    "BlockDec": -6,
    "Hit": "STN",
    "HitDec": null,
    "CounterHit": "STN",
    "CounterHitDec": null,
    "GuardBurst": 10,
    "Notes": "On hit, 2nd hit cannot be evaded but can be GId | Gains meter"
  },
  {
    "ID": 3022,
    "stringCommand": ":B::B::A:",
    "Command": [
      "B",
      "B",
      "A"
    ],
    "Stance": null,
    "HitLevel": [
      "M",
      "M",
      "L"
    ],
    "Impact": 20,
    "Damage": "14,12,18",
    "DamageDec": 44,
    "Block": "-14",
    "BlockDec": -14,
    "Hit": "-4",
    "HitDec": -4,
    "CounterHit": "-4",
    "CounterHitDec": -4,
    "GuardBurst": 6,
    "Notes": "NCC. Trades with i14 on guard."
  },
  {
    "ID": 3023,
    "stringCommand": ":B::B::B:",
    "Command": [
      "B",
      "B",
      "B"
    ],
    "Stance": null,
    "HitLevel": [
      "M",
      "M",
      "M"
    ],
    "Impact": 20,
    "Damage": "14,12,28",
    "DamageDec": 54,
    "Block": "-16",
    "BlockDec": -16,
    "Hit": "KND",
    "HitDec": null,
    "CounterHit": "KND",
    "CounterHitDec": null,
    "GuardBurst": 14,
    "Notes": "NCC. Uninteruptable but 3rd hit can be dodged."
  },
  {
    "ID": 3024,
    "stringCommand": ":B::B::(B):",
    "Command": [
      "B",
      "B",
      "(B)"
    ],
    "Stance": null,
    "HitLevel": [
      "M",
      "M",
      "M"
    ],
    "Impact": 20,
    "Damage": "14,12,34",
    "DamageDec": 60,
    "Block": "4",
    "BlockDec": 4,
    "Hit": "KND",
    "HitDec": null,
    "CounterHit": "KND",
    "CounterHitDec": null,
    "GuardBurst": 25,
    "Notes": "NCC. :BA:"
  },
  {
    "ID": 3025,
    "stringCommand": ":B::(B)::(B):",
    "Command": [
      "B",
      "(B)",
      "(B)"
    ],
    "Stance": null,
    "HitLevel": [
      "M",
      "M",
      "M"
    ],
    "Impact": 20,
    "Damage": "14,12,34",
    "DamageDec": 60,
    "Block": "4",
    "BlockDec": 4,
    "Hit": "KND",
    "HitDec": null,
    "CounterHit": "KND",
    "CounterHitDec": null,
    "GuardBurst": 29,
    "Notes": ":BA:"
  },
  {
    "ID": 3026,
    "stringCommand": ":B::4::B:",
    "Command": [
      "B",
      "4",
      "B"
    ],
    "Stance": null,
    "HitLevel": [
      "M",
      "H"
    ],
    "Impact": 20,
    "Damage": "14,1",
    "DamageDec": 15,
    "Block": "-14",
    "BlockDec": -14,
    "Hit": "-2",
    "HitDec": -2,
    "CounterHit": "-2",
    "CounterHitDec": -2,
    "GuardBurst": 4,
    "Notes": "NC. :SS: into LS"
  },
  {
    "ID": 3027,
    "stringCommand": ":b::A:",
    "Command": [
      "b",
      "A"
    ],
    "Stance": null,
    "HitLevel": [
      "H",
      "H"
    ],
    "Impact": 20,
    "Damage": "12,18",
    "DamageDec": 30,
    "Block": "-6",
    "BlockDec": -6,
    "Hit": "KND",
    "HitDec": null,
    "CounterHit": "KND",
    "CounterHitDec": null,
    "GuardBurst": 2,
    "Notes": "NC. Jails."
  },
  {
    "ID": 3028,
    "stringCommand": ":B::6:",
    "Command": [
      "B",
      "6"
    ],
    "Stance": null,
    "HitLevel": [
      "H",
      "H"
    ],
    "Impact": 16,
    "Damage": "32",
    "DamageDec": 32,
    "Block": "-8",
    "BlockDec": -8,
    "Hit": "KND",
    "HitDec": null,
    "CounterHit": "KND",
    "CounterHitDec": null,
    "GuardBurst": 9,
    "Notes": "NC. Jails."
  },
  {
    "ID": 3029,
    "stringCommand": ":6::B:",
    "Command": [
      "6",
      "B"
    ],
    "Stance": null,
    "HitLevel": [
      "M"
    ],
    "Impact": 20,
    "Damage": "36",
    "DamageDec": 36,
    "Block": "-12",
    "BlockDec": -12,
    "Hit": "KND",
    "HitDec": null,
    "CounterHit": "KND",
    "CounterHitDec": null,
    "GuardBurst": 9,
    "Notes": "TC. :LH: on back step counterhit"
  },
  {
    "ID": 3030,
    "stringCommand": ":6::b::A:",
    "Command": [
      "6",
      "b",
      "A"
    ],
    "Stance": null,
    "HitLevel": [
      "M"
    ],
    "Impact": 28,
    "Damage": "20",
    "DamageDec": 20,
    "Block": "-8",
    "BlockDec": -8,
    "Hit": "4",
    "HitDec": 4,
    "CounterHit": "4",
    "CounterHitDec": 4,
    "GuardBurst": 1,
    "Notes": null
  },
  {
    "ID": 3031,
    "stringCommand": ":6::b::A:",
    "Command": [
      "6",
      "b",
      "A"
    ],
    "Stance": [
      "tip range"
    ],
    "HitLevel": [
      "M"
    ],
    "Impact": 28,
    "Damage": "28",
    "DamageDec": 28,
    "Block": "2",
    "BlockDec": 2,
    "Hit": "KND",
    "HitDec": null,
    "CounterHit": "KND",
    "CounterHitDec": null,
    "GuardBurst": 4,
    "Notes": null
  },
  {
    "ID": 3032,
    "stringCommand": ":3::B:",
    "Command": [
      "3",
      "B"
    ],
    "Stance": null,
    "HitLevel": [
      "M"
    ],
    "Impact": 20,
    "Damage": "22",
    "DamageDec": 22,
    "Block": "-14",
    "BlockDec": -14,
    "Hit": "LNC",
    "HitDec": null,
    "CounterHit": "LNC",
    "CounterHitDec": null,
    "GuardBurst": 9,
    "Notes": null
  },
  {
    "ID": 3033,
    "stringCommand": ":3::B:",
    "Command": [
      "3",
      "B"
    ],
    "Stance": [
      "tip range"
    ],
    "HitLevel": [
      "M"
    ],
    "Impact": 20,
    "Damage": "28",
    "DamageDec": 28,
    "Block": "-14",
    "BlockDec": -14,
    "Hit": "LNC",
    "HitDec": null,
    "CounterHit": "LNC",
    "CounterHitDec": null,
    "GuardBurst": 9,
    "Notes": null
  },
  {
    "ID": 3034,
    "stringCommand": ":2::B:",
    "Command": [
      "2",
      "B"
    ],
    "Stance": null,
    "HitLevel": [
      "M"
    ],
    "Impact": 18,
    "Damage": "16",
    "DamageDec": 16,
    "Block": "-10",
    "BlockDec": -10,
    "Hit": "2",
    "HitDec": 2,
    "CounterHit": "8",
    "CounterHitDec": 8,
    "GuardBurst": 2,
    "Notes": null
  },
  {
    "ID": 3035,
    "stringCommand": ":2::B:",
    "Command": [
      "2",
      "B"
    ],
    "Stance": [
      "tip range"
    ],
    "HitLevel": [
      "M"
    ],
    "Impact": 18,
    "Damage": "20",
    "DamageDec": 20,
    "Block": "-10",
    "BlockDec": -10,
    "Hit": "6",
    "HitDec": 6,
    "CounterHit": "8",
    "CounterHitDec": 8,
    "GuardBurst": 2,
    "Notes": null
  },
  {
    "ID": 3036,
    "stringCommand": ":2::B::A:",
    "Command": [
      "2",
      "B",
      "A"
    ],
    "Stance": null,
    "HitLevel": [
      "M",
      "L"
    ],
    "Impact": 18,
    "Damage": "10,3",
    "DamageDec": 13,
    "Block": "-8",
    "BlockDec": -8,
    "Hit": "KND",
    "HitDec": null,
    "CounterHit": "KND",
    "CounterHitDec": null,
    "GuardBurst": 4,
    "Notes": "Trades with i17 on guard."
  },
  {
    "ID": 3037,
    "stringCommand": ":2::B::B:",
    "Command": [
      "2",
      "B",
      "B"
    ],
    "Stance": null,
    "HitLevel": [
      "M",
      "H"
    ],
    "Impact": 18,
    "Damage": "10,1",
    "DamageDec": 11,
    "Block": "-14",
    "BlockDec": -14,
    "Hit": "-2",
    "HitDec": -2,
    "CounterHit": "-2",
    "CounterHitDec": -2,
    "GuardBurst": 4,
    "Notes": "NC. :SS: into LS. :LH: anytime after breaking opponents guard"
  },
  {
    "ID": 3038,
    "stringCommand": ":2::B::K:",
    "Command": [
      "2",
      "B",
      "C"
    ],
    "Stance": null,
    "HitLevel": [
      "M",
      "M"
    ],
    "Impact": 18,
    "Damage": "10,2",
    "DamageDec": 12,
    "Block": "-8",
    "BlockDec": -8,
    "Hit": "KND",
    "HitDec": null,
    "CounterHit": "KND",
    "CounterHitDec": null,
    "GuardBurst": 5,
    "Notes": "NC on tip range. :NCC. on all ranges. TJ. Delayable"
  },
  {
    "ID": 3039,
    "stringCommand": ":2::3::6::B:",
    "Command": [
      "2",
      "3",
      "6",
      "B"
    ],
    "Stance": null,
    "HitLevel": [
      "M"
    ],
    "Impact": 24,
    "Damage": "28",
    "DamageDec": 28,
    "Block": "-8",
    "BlockDec": -8,
    "Hit": "LNC",
    "HitDec": null,
    "CounterHit": "LNC",
    "CounterHitDec": null,
    "GuardBurst": 9,
    "Notes": ":LH: when winning round with CE"
  },
  {
    "ID": 3040,
    "stringCommand": ":2::3::6::B::A:",
    "Command": [
      "2",
      "3",
      "6",
      "B",
      "A"
    ],
    "Stance": null,
    "HitLevel": [
      "M",
      "H",
      "H",
      "H",
      "H",
      "M"
    ],
    "Impact": 24,
    "Damage": "28,3,3,3,2,13",
    "DamageDec": 52,
    "Block": "-12",
    "BlockDec": -12,
    "Hit": "KND",
    "HitDec": null,
    "CounterHit": "KND",
    "CounterHitDec": null,
    "GuardBurst": 15,
    "Notes": "NC"
  },
  {
    "ID": 3041,
    "stringCommand": ":2::3::6::B::B:",
    "Command": [
      "2",
      "3",
      "6",
      "B",
      "B"
    ],
    "Stance": null,
    "HitLevel": [
      "M",
      "M"
    ],
    "Impact": 24,
    "Damage": "28,48",
    "DamageDec": 76,
    "Block": "-10",
    "BlockDec": -10,
    "Hit": "KND",
    "HitDec": null,
    "CounterHit": "KND",
    "CounterHitDec": null,
    "GuardBurst": null,
    "Notes": "NC. Forces crouch."
  },
  {
    "ID": 3042,
    "stringCommand": ":2::3::6::B::(B):",
    "Command": [
      "2",
      "3",
      "6",
      "B",
      "(B)"
    ],
    "Stance": null,
    "HitLevel": [
      "M",
      "M"
    ],
    "Impact": 24,
    "Damage": "28,52",
    "DamageDec": 80,
    "Block": "0",
    "BlockDec": 0,
    "Hit": "STN",
    "HitDec": null,
    "CounterHit": "STN",
    "CounterHitDec": null,
    "GuardBurst": 50,
    "Notes": "NC. Forces crouch."
  },
  {
    "ID": 3043,
    "stringCommand": ":2::3::6::B::K:",
    "Command": [
      "2",
      "3",
      "6",
      "B",
      "C"
    ],
    "Stance": null,
    "HitLevel": [
      "M",
      "M"
    ],
    "Impact": 24,
    "Damage": "28,3",
    "DamageDec": 31,
    "Block": "0",
    "BlockDec": 0,
    "Hit": "KND",
    "HitDec": null,
    "CounterHit": "KND",
    "CounterHitDec": null,
    "GuardBurst": 13,
    "Notes": "NC. Forces crouch."
  },
  {
    "ID": 3044,
    "stringCommand": ":1::B:",
    "Command": [
      "1",
      "B"
    ],
    "Stance": null,
    "HitLevel": [
      "L"
    ],
    "Impact": 22,
    "Damage": "22",
    "DamageDec": 22,
    "Block": "-20",
    "BlockDec": -20,
    "Hit": "-8",
    "HitDec": -8,
    "CounterHit": "-8",
    "CounterHitDec": -8,
    "GuardBurst": 2,
    "Notes": "TC. Guard cancellable"
  },
  {
    "ID": 3045,
    "stringCommand": ":1::B:",
    "Command": [
      "1",
      "B"
    ],
    "Stance": [
      "tip range"
    ],
    "HitLevel": [
      "L"
    ],
    "Impact": 22,
    "Damage": "36",
    "DamageDec": 36,
    "Block": "-10",
    "BlockDec": -10,
    "Hit": "KND",
    "HitDec": null,
    "CounterHit": "KND",
    "CounterHitDec": null,
    "GuardBurst": 9,
    "Notes": "TC. Guard cancellable"
  },
  {
    "ID": 3046,
    "stringCommand": ":4::B:",
    "Command": [
      "4",
      "B"
    ],
    "Stance": null,
    "HitLevel": [
      "H"
    ],
    "Impact": 14,
    "Damage": "18",
    "DamageDec": 18,
    "Block": "-14",
    "BlockDec": -14,
    "Hit": "2",
    "HitDec": 2,
    "CounterHit": "2",
    "CounterHitDec": 2,
    "GuardBurst": 2,
    "Notes": ":SS: into LS"
  },
  {
    "ID": 3047,
    "stringCommand": ":7::B:",
    "Command": [
      "7",
      "B"
    ],
    "Stance": null,
    "HitLevel": [
      "M"
    ],
    "Impact": 36,
    "Damage": "25",
    "DamageDec": 25,
    "Block": "-16",
    "BlockDec": -16,
    "Hit": "LNC",
    "HitDec": null,
    "CounterHit": "LNC",
    "CounterHitDec": null,
    "GuardBurst": 9,
    "Notes": "TJ[4-?]"
  },
  {
    "ID": 3048,
    "stringCommand": ":8::B:",
    "Command": [
      "8",
      "B"
    ],
    "Stance": null,
    "HitLevel": [
      "M"
    ],
    "Impact": 36,
    "Damage": "25",
    "DamageDec": 25,
    "Block": "-12",
    "BlockDec": -12,
    "Hit": "LNC",
    "HitDec": null,
    "CounterHit": "LNC",
    "CounterHitDec": null,
    "GuardBurst": 9,
    "Notes": "TJ[4-?]"
  },
  {
    "ID": 3049,
    "stringCommand": ":2::B:",
    "Command": [
      "2",
      "B"
    ],
    "Stance": [
      "FC"
    ],
    "HitLevel": [
      "M"
    ],
    "Impact": 36,
    "Damage": "20",
    "DamageDec": 20,
    "Block": "-6",
    "BlockDec": -6,
    "Hit": "2",
    "HitDec": 2,
    "CounterHit": "2",
    "CounterHitDec": 2,
    "GuardBurst": 2,
    "Notes": "TC[?-RC]"
  },
  {
    "ID": 3050,
    "stringCommand": ":2::B::B:",
    "Command": [
      "2",
      "B",
      "B"
    ],
    "Stance": [
      "FC"
    ],
    "HitLevel": [
      "M",
      "L"
    ],
    "Impact": 18,
    "Damage": "20,22",
    "DamageDec": 42,
    "Block": "-6",
    "BlockDec": -6,
    "Hit": "4",
    "HitDec": 4,
    "CounterHit": "4",
    "CounterHitDec": 4,
    "GuardBurst": 4,
    "Notes": "TC[?-RC]"
  },
  {
    "ID": 3051,
    "stringCommand": ":B:",
    "Command": [
      "B"
    ],
    "Stance": [
      "WR"
    ],
    "HitLevel": [
      "M"
    ],
    "Impact": 18,
    "Damage": "22",
    "DamageDec": 22,
    "Block": "-10",
    "BlockDec": -10,
    "Hit": "KND",
    "HitDec": null,
    "CounterHit": "KND",
    "CounterHitDec": null,
    "GuardBurst": 9,
    "Notes": "-8 on block at max range"
  },
  {
    "ID": 3052,
    "stringCommand": ":B:",
    "Command": [
      "B"
    ],
    "Stance": [
      "BT"
    ],
    "HitLevel": [
      "M"
    ],
    "Impact": 22,
    "Damage": "20",
    "DamageDec": 20,
    "Block": "-6",
    "BlockDec": -6,
    "Hit": "LNC",
    "HitDec": null,
    "CounterHit": "LNC",
    "CounterHitDec": null,
    "GuardBurst": 2,
    "Notes": "TC[22-39]"
  },
  {
    "ID": 3053,
    "stringCommand": ":2::B:",
    "Command": [
      "2",
      "B"
    ],
    "Stance": [
      "BT"
    ],
    "HitLevel": [
      "M"
    ],
    "Impact": 22,
    "Damage": "24",
    "DamageDec": 24,
    "Block": "-8",
    "BlockDec": -8,
    "Hit": "2",
    "HitDec": 2,
    "CounterHit": "2",
    "CounterHitDec": 2,
    "GuardBurst": 2,
    "Notes": "TC[4-RC]"
  },
  {
    "ID": 3054,
    "stringCommand": ":K:",
    "Command": [
      "C"
    ],
    "Stance": null,
    "HitLevel": [
      "H"
    ],
    "Impact": 12,
    "Damage": "14",
    "DamageDec": 14,
    "Block": "-8",
    "BlockDec": -8,
    "Hit": "0",
    "HitDec": 0,
    "CounterHit": "0",
    "CounterHitDec": 0,
    "GuardBurst": 1,
    "Notes": null
  },
  {
    "ID": 3055,
    "stringCommand": ":6::K:",
    "Command": [
      "6",
      "C"
    ],
    "Stance": null,
    "HitLevel": [
      "M"
    ],
    "Impact": 22,
    "Damage": "24",
    "DamageDec": 24,
    "Block": "-8",
    "BlockDec": -8,
    "Hit": "KND",
    "HitDec": null,
    "CounterHit": "KND",
    "CounterHitDec": null,
    "GuardBurst": 9,
    "Notes": "GI[3-12] vs high/mid verticals (except kicks)"
  },
  {
    "ID": 3056,
    "stringCommand": ":3::K:",
    "Command": [
      "3",
      "C"
    ],
    "Stance": null,
    "HitLevel": [
      "M"
    ],
    "Impact": 14,
    "Damage": "10",
    "DamageDec": 10,
    "Block": "-12",
    "BlockDec": -12,
    "Hit": "-4",
    "HitDec": -4,
    "CounterHit": "-4",
    "CounterHitDec": -4,
    "GuardBurst": 2,
    "Notes": null
  },
  {
    "ID": 3057,
    "stringCommand": ":3::K::K:",
    "Command": [
      "3",
      "C",
      "C"
    ],
    "Stance": null,
    "HitLevel": [
      "M",
      "H"
    ],
    "Impact": 14,
    "Damage": "10,14",
    "DamageDec": 24,
    "Block": "-8",
    "BlockDec": -8,
    "Hit": "0",
    "HitDec": 0,
    "CounterHit": "STN",
    "CounterHitDec": null,
    "GuardBurst": 4,
    "Notes": "NC"
  },
  {
    "ID": 3058,
    "stringCommand": ":3::b::K:",
    "Command": [
      "3",
      "b",
      "C"
    ],
    "Stance": null,
    "HitLevel": [
      "M"
    ],
    "Impact": 14,
    "Damage": "20",
    "DamageDec": 20,
    "Block": "-14",
    "BlockDec": -14,
    "Hit": "KND",
    "HitDec": null,
    "CounterHit": "KND",
    "CounterHitDec": null,
    "GuardBurst": 9,
    "Notes": "8 more damage with perfect input"
  },
  {
    "ID": 3059,
    "stringCommand": ":2::K:",
    "Command": [
      "2",
      "C"
    ],
    "Stance": null,
    "HitLevel": [
      "L"
    ],
    "Impact": 16,
    "Damage": "12",
    "DamageDec": 12,
    "Block": "-14",
    "BlockDec": -14,
    "Hit": "-4",
    "HitDec": -4,
    "CounterHit": "-4",
    "CounterHitDec": -4,
    "GuardBurst": 1,
    "Notes": "TC[?-RC]"
  },
  {
    "ID": 3060,
    "stringCommand": ":1::K:",
    "Command": [
      "1",
      "C"
    ],
    "Stance": null,
    "HitLevel": [
      "L"
    ],
    "Impact": 22,
    "Damage": "24",
    "DamageDec": 24,
    "Block": "-18",
    "BlockDec": -18,
    "Hit": "-6",
    "HitDec": -6,
    "CounterHit": "-6",
    "CounterHitDec": -6,
    "GuardBurst": 9,
    "Notes": null
  },
  {
    "ID": 3061,
    "stringCommand": ":4::K:",
    "Command": [
      "4",
      "C"
    ],
    "Stance": null,
    "HitLevel": [
      "M"
    ],
    "Impact": 22,
    "Damage": "10",
    "DamageDec": 10,
    "Block": "-14",
    "BlockDec": -14,
    "Hit": "0",
    "HitDec": 0,
    "CounterHit": "0",
    "CounterHitDec": 0,
    "GuardBurst": 2,
    "Notes": "GI[7-18] vs high/mid horizontals (except kicks)"
  },
  {
    "ID": 3062,
    "stringCommand": ":4::K::B:",
    "Command": [
      "4",
      "C",
      "B"
    ],
    "Stance": null,
    "HitLevel": [
      "M",
      "M"
    ],
    "Impact": 22,
    "Damage": "10,22",
    "DamageDec": 32,
    "Block": "-14",
    "BlockDec": -14,
    "Hit": "0",
    "HitDec": 0,
    "CounterHit": "0",
    "CounterHitDec": 0,
    "GuardBurst": 9,
    "Notes": "NC. Delayable. +18 when GIs"
  },
  {
    "ID": 3063,
    "stringCommand": ":2::K:",
    "Command": [
      "2",
      "C"
    ],
    "Stance": [
      "FC"
    ],
    "HitLevel": [
      "L"
    ],
    "Impact": 16,
    "Damage": "12",
    "DamageDec": 12,
    "Block": "-14",
    "BlockDec": -14,
    "Hit": "-4",
    "HitDec": -4,
    "CounterHit": "-4",
    "CounterHitDec": -4,
    "GuardBurst": 1,
    "Notes": "TC[?-RC]"
  },
  {
    "ID": 3064,
    "stringCommand": ":1::K:",
    "Command": [
      "1",
      "C"
    ],
    "Stance": [
      "FC"
    ],
    "HitLevel": [
      "L"
    ],
    "Impact": 20,
    "Damage": "15",
    "DamageDec": 15,
    "Block": "-24",
    "BlockDec": -24,
    "Hit": "-4",
    "HitDec": -4,
    "CounterHit": "KND",
    "CounterHitDec": null,
    "GuardBurst": 4,
    "Notes": "TC"
  },
  {
    "ID": 3065,
    "stringCommand": ":1::K:",
    "Command": [
      "1",
      "C"
    ],
    "Stance": [
      "Tip",
      "FC"
    ],
    "HitLevel": [
      "L"
    ],
    "Impact": 20,
    "Damage": "15",
    "DamageDec": 15,
    "Block": "-24",
    "BlockDec": -24,
    "Hit": "-4",
    "HitDec": -4,
    "CounterHit": "KND",
    "CounterHitDec": null,
    "GuardBurst": 4,
    "Notes": "TC"
  },
  {
    "ID": 3066,
    "stringCommand": ":1::K::K:",
    "Command": [
      "1",
      "C",
      "C"
    ],
    "Stance": [
      "FC"
    ],
    "HitLevel": [
      "L",
      "L"
    ],
    "Impact": 20,
    "Damage": "15,19",
    "DamageDec": 34,
    "Block": "-22",
    "BlockDec": -22,
    "Hit": "KND",
    "HitDec": null,
    "CounterHit": "KND",
    "CounterHitDec": null,
    "GuardBurst": 5,
    "Notes": "NC. TC"
  },
  {
    "ID": 3067,
    "stringCommand": ":1::K::K:",
    "Command": [
      "1",
      "C",
      "C"
    ],
    "Stance": [
      "Tip",
      "FC"
    ],
    "HitLevel": [
      "L",
      "L"
    ],
    "Impact": 20,
    "Damage": "15,19",
    "DamageDec": 34,
    "Block": "-22",
    "BlockDec": -22,
    "Hit": "KND",
    "HitDec": null,
    "CounterHit": "KND",
    "CounterHitDec": null,
    "GuardBurst": 5,
    "Notes": "NC. TC"
  },
  {
    "ID": 3068,
    "stringCommand": ":K:",
    "Command": [
      "C"
    ],
    "Stance": [
      "WR"
    ],
    "HitLevel": [
      "M"
    ],
    "Impact": 12,
    "Damage": "20",
    "DamageDec": 20,
    "Block": "-16",
    "BlockDec": -16,
    "Hit": "KND",
    "HitDec": null,
    "CounterHit": "KND",
    "CounterHitDec": null,
    "GuardBurst": 9,
    "Notes": "TC"
  },
  {
    "ID": 3069,
    "stringCommand": ":7::K:",
    "Command": [
      "7",
      "C"
    ],
    "Stance": null,
    "HitLevel": [
      "M"
    ],
    "Impact": 18,
    "Damage": "16",
    "DamageDec": 16,
    "Block": "-14",
    "BlockDec": -14,
    "Hit": "-4",
    "HitDec": -4,
    "CounterHit": "-4",
    "CounterHitDec": -4,
    "GuardBurst": 2,
    "Notes": "TJ[4-?]"
  },
  {
    "ID": 3070,
    "stringCommand": ":8::K:",
    "Command": [
      "8",
      "C"
    ],
    "Stance": null,
    "HitLevel": [
      "M"
    ],
    "Impact": 18,
    "Damage": "18",
    "DamageDec": 18,
    "Block": "-8",
    "BlockDec": -8,
    "Hit": "0",
    "HitDec": 0,
    "CounterHit": "0",
    "CounterHitDec": 0,
    "GuardBurst": 2,
    "Notes": "TJ[4-?]"
  },
  {
    "ID": 3071,
    "stringCommand": ":9::K:",
    "Command": [
      "9",
      "C"
    ],
    "Stance": null,
    "HitLevel": [
      "M"
    ],
    "Impact": 18,
    "Damage": "20",
    "DamageDec": 20,
    "Block": "-8",
    "BlockDec": -8,
    "Hit": "0",
    "HitDec": 0,
    "CounterHit": "0",
    "CounterHitDec": 0,
    "GuardBurst": 2,
    "Notes": "TJ[4-?]"
  },
  {
    "ID": 3072,
    "stringCommand": ":K:",
    "Command": [
      "C"
    ],
    "Stance": [
      "BT"
    ],
    "HitLevel": [
      "H"
    ],
    "Impact": 14,
    "Damage": "18",
    "DamageDec": 18,
    "Block": "-6",
    "BlockDec": -6,
    "Hit": "4",
    "HitDec": 4,
    "CounterHit": "4",
    "CounterHitDec": 4,
    "GuardBurst": 1,
    "Notes": null
  },
  {
    "ID": 3073,
    "stringCommand": ":2::K:",
    "Command": [
      "2",
      "C"
    ],
    "Stance": [
      "BT"
    ],
    "HitLevel": [
      "L"
    ],
    "Impact": 18,
    "Damage": "16",
    "DamageDec": 16,
    "Block": "-14",
    "BlockDec": -14,
    "Hit": "-4",
    "HitDec": -4,
    "CounterHit": "-4",
    "CounterHitDec": -4,
    "GuardBurst": 1,
    "Notes": "TC[19-RC]"
  },
  {
    "ID": 3074,
    "stringCommand": ":A+B:",
    "Command": [
      "A+B"
    ],
    "Stance": null,
    "HitLevel": [
      "M"
    ],
    "Impact": 38,
    "Damage": "36",
    "DamageDec": 36,
    "Block": "10",
    "BlockDec": 10,
    "Hit": "LNC",
    "HitDec": null,
    "CounterHit": "LNC",
    "CounterHitDec": null,
    "GuardBurst": 15,
    "Notes": ":BA:. :LH: on impact counter. 40 dmg at tip range"
  },
  {
    "ID": 3075,
    "stringCommand": ":6::A+B:",
    "Command": [
      "6",
      "A+B"
    ],
    "Stance": null,
    "HitLevel": [
      "H"
    ],
    "Impact": 18,
    "Damage": "26",
    "DamageDec": 26,
    "Block": "-8",
    "BlockDec": -8,
    "Hit": "2",
    "HitDec": 2,
    "CounterHit": "2",
    "CounterHitDec": 2,
    "GuardBurst": 1,
    "Notes": null
  },
  {
    "ID": 3076,
    "stringCommand": ":3::A+B:",
    "Command": [
      "3",
      "A+B"
    ],
    "Stance": null,
    "HitLevel": [
      "M",
      "M",
      "M"
    ],
    "Impact": 24,
    "Damage": "8,8,18",
    "DamageDec": 34,
    "Block": "-10",
    "BlockDec": -10,
    "Hit": "2",
    "HitDec": 2,
    "CounterHit": "2",
    "CounterHitDec": 2,
    "GuardBurst": 4,
    "Notes": "NC. TC. Jails"
  },
  {
    "ID": 3077,
    "stringCommand": ":3::(A)+(B):",
    "Command": [
      "3",
      "(A)+(B)"
    ],
    "Stance": null,
    "HitLevel": [
      "M",
      "M",
      "M",
      "M"
    ],
    "Impact": 40,
    "Damage": "12,12,12,22",
    "DamageDec": 58,
    "Block": "0",
    "BlockDec": 0,
    "Hit": "KND",
    "HitDec": null,
    "CounterHit": "KND",
    "CounterHitDec": null,
    "GuardBurst": 9,
    "Notes": "NC. TC. Jails"
  },
  {
    "ID": 3078,
    "stringCommand": ":2::A+B:",
    "Command": [
      "2",
      "A+B"
    ],
    "Stance": null,
    "HitLevel": [
      "L"
    ],
    "Impact": 36,
    "Damage": "28",
    "DamageDec": 28,
    "Block": "0",
    "BlockDec": 0,
    "Hit": "4",
    "HitDec": 4,
    "CounterHit": "KND",
    "CounterHitDec": null,
    "GuardBurst": 9,
    "Notes": ":BA:. :LH: on red guard gauge. Guard cancellable. RC"
  },
  {
    "ID": 3079,
    "stringCommand": ":2::A+B:",
    "Command": [
      "2",
      "A+B"
    ],
    "Stance": [
      "tip range"
    ],
    "HitLevel": [
      "L"
    ],
    "Impact": 36,
    "Damage": "34",
    "DamageDec": 34,
    "Block": "4",
    "BlockDec": 4,
    "Hit": "KND",
    "HitDec": null,
    "CounterHit": "KND",
    "CounterHitDec": null,
    "GuardBurst": 9,
    "Notes": ":BA:. :LH: on red guard gauge. Guard cancellable. RC"
  },
  {
    "ID": 3080,
    "stringCommand": ":4::A+B:",
    "Command": [
      "4",
      "A+B"
    ],
    "Stance": null,
    "HitLevel": [
      "M"
    ],
    "Impact": 16,
    "Damage": "5,5,5,5",
    "DamageDec": 20,
    "Block": "-8",
    "BlockDec": -8,
    "Hit": "0",
    "HitDec": 0,
    "CounterHit": "0",
    "CounterHitDec": 0,
    "GuardBurst": 7,
    "Notes": null
  },
  {
    "ID": 3081,
    "stringCommand": ":4::A+B::A:",
    "Command": [
      "4",
      "A+B",
      "A"
    ],
    "Stance": null,
    "HitLevel": [
      "M",
      "H"
    ],
    "Impact": 16,
    "Damage": "5,5,5,21",
    "DamageDec": 36,
    "Block": "-8",
    "BlockDec": -8,
    "Hit": "2",
    "HitDec": 2,
    "CounterHit": "2",
    "CounterHitDec": 2,
    "GuardBurst": 7,
    "Notes": "Close hit ends in both being BT. Mid to far range ends facing foward"
  },
  {
    "ID": 3082,
    "stringCommand": ":4::A+B::A::B:",
    "Command": [
      "4",
      "A+B",
      "A",
      "B"
    ],
    "Stance": null,
    "HitLevel": [
      "M",
      "H",
      "M"
    ],
    "Impact": 16,
    "Damage": "5,5,5,21,36",
    "DamageDec": 72,
    "Block": "4",
    "BlockDec": 4,
    "Hit": "KND",
    "HitDec": null,
    "CounterHit": "KND",
    "CounterHitDec": null,
    "GuardBurst": 17,
    "Notes": ":BA:. NCC if A hits"
  },
  {
    "ID": 3083,
    "stringCommand": ":4::A+B::A+B:",
    "Command": [
      "4",
      "A+B",
      "A+B"
    ],
    "Stance": null,
    "HitLevel": [
      "M",
      "M"
    ],
    "Impact": 16,
    "Damage": "5,5,5,5,5,5,20",
    "DamageDec": 50,
    "Block": "-8",
    "BlockDec": -8,
    "Hit": "2",
    "HitDec": 2,
    "CounterHit": "2",
    "CounterHitDec": 2,
    "GuardBurst": 13,
    "Notes": "If any hit of second A+B hits, the rest of the attack combos"
  },
  {
    "ID": 3084,
    "stringCommand": ":8::A+B:",
    "Command": [
      "8",
      "A+B"
    ],
    "Stance": null,
    "HitLevel": [
      "M"
    ],
    "Impact": 18,
    "Damage": "35",
    "DamageDec": 35,
    "Block": "-20",
    "BlockDec": -20,
    "Hit": "KND",
    "HitDec": null,
    "CounterHit": "KND",
    "CounterHitDec": null,
    "GuardBurst": 4,
    "Notes": "TC & TJ"
  },
  {
    "ID": 3085,
    "stringCommand": ":9::A+B:",
    "Command": [
      "9",
      "A+B"
    ],
    "Stance": null,
    "HitLevel": [
      "M"
    ],
    "Impact": 84,
    "Damage": "100",
    "DamageDec": 100,
    "Block": "-",
    "BlockDec": null,
    "Hit": "KND",
    "HitDec": null,
    "CounterHit": "KND",
    "CounterHitDec": null,
    "GuardBurst": null,
    "Notes": ":UA:. Guard cancel :SS: into LS"
  },
  {
    "ID": 3086,
    "stringCommand": ":9::A+B::B:",
    "Command": [
      "9",
      "A+B",
      "B"
    ],
    "Stance": null,
    "HitLevel": [
      "M"
    ],
    "Impact": 67,
    "Damage": "60",
    "DamageDec": 60,
    "Block": "16",
    "BlockDec": 16,
    "Hit": "KND",
    "HitDec": null,
    "CounterHit": "KND",
    "CounterHitDec": null,
    "GuardBurst": 15,
    "Notes": ":BA:. :LH: on impact counter"
  },
  {
    "ID": 3087,
    "stringCommand": ":B+K:",
    "Command": [
      "B+C"
    ],
    "Stance": null,
    "HitLevel": [
      "M",
      "M"
    ],
    "Impact": 24,
    "Damage": "42",
    "DamageDec": 42,
    "Block": "-26 -18",
    "BlockDec": -26,
    "Hit": "KND",
    "HitDec": null,
    "CounterHit": "KND",
    "CounterHitDec": null,
    "GuardBurst": 14,
    "Notes": "NC"
  },
  {
    "ID": 3088,
    "stringCommand": ":6::B+K:",
    "Command": [
      "6",
      "B+C"
    ],
    "Stance": null,
    "HitLevel": [
      "M",
      "M",
      "M",
      "M",
      "M"
    ],
    "Impact": 18,
    "Damage": "12,12,8,8,12",
    "DamageDec": 52,
    "Block": "-14",
    "BlockDec": -14,
    "Hit": "KND",
    "HitDec": null,
    "CounterHit": "KND",
    "CounterHitDec": null,
    "GuardBurst": 12,
    "Notes": "NCC"
  },
  {
    "ID": 3089,
    "stringCommand": ":2::B+K:",
    "Command": [
      "2",
      "B+C"
    ],
    "Stance": null,
    "HitLevel": [
      "L"
    ],
    "Impact": 22,
    "Damage": "18",
    "DamageDec": 18,
    "Block": "-16",
    "BlockDec": -16,
    "Hit": "-2",
    "HitDec": -2,
    "CounterHit": "KND",
    "CounterHitDec": null,
    "GuardBurst": 2,
    "Notes": "Forces crouch on hit"
  },
  {
    "ID": 3090,
    "stringCommand": ":2::B+K:",
    "Command": [
      "2",
      "B+C"
    ],
    "Stance": [
      "tip range"
    ],
    "HitLevel": [
      "L"
    ],
    "Impact": 22,
    "Damage": "22",
    "DamageDec": 22,
    "Block": "-16",
    "BlockDec": -16,
    "Hit": "16",
    "HitDec": 16,
    "CounterHit": "STN",
    "CounterHitDec": null,
    "GuardBurst": 2,
    "Notes": null
  },
  {
    "ID": 3091,
    "stringCommand": ":4::B+K:",
    "Command": [
      "4",
      "B+C"
    ],
    "Stance": null,
    "HitLevel": [
      "M",
      "M",
      "M",
      "M",
      "M"
    ],
    "Impact": 36,
    "Damage": "30",
    "DamageDec": 30,
    "Block": "-6",
    "BlockDec": -6,
    "Hit": "KND",
    "HitDec": null,
    "CounterHit": "KND",
    "CounterHitDec": null,
    "GuardBurst": 18,
    "Notes": ":GI:[3-18] vs high/mid verticals (not kicks). :TS:"
  },
  {
    "ID": 3092,
    "stringCommand": ":8::B+K:",
    "Command": [
      "8",
      "B+C"
    ],
    "Stance": null,
    "HitLevel": [
      "M"
    ],
    "Impact": 21,
    "Damage": "16",
    "DamageDec": 16,
    "Block": "-14",
    "BlockDec": -14,
    "Hit": "2",
    "HitDec": 2,
    "CounterHit": "2",
    "CounterHitDec": 2,
    "GuardBurst": 9,
    "Notes": "TJ. Forces crouch on hit"
  },
  {
    "ID": 3093,
    "stringCommand": ":8::B+K::B:",
    "Command": [
      "8",
      "B+C",
      "B"
    ],
    "Stance": null,
    "HitLevel": [
      "M",
      "M"
    ],
    "Impact": 21,
    "Damage": "16,10",
    "DamageDec": 26,
    "Block": "-14",
    "BlockDec": -14,
    "Hit": "2",
    "HitDec": 2,
    "CounterHit": "2",
    "CounterHitDec": 2,
    "GuardBurst": 10,
    "Notes": "NC. TJ. Forces crouch on hit"
  },
  {
    "ID": 3094,
    "stringCommand": ":8::B+K::B::B:",
    "Command": [
      "8",
      "B+C",
      "B",
      "B"
    ],
    "Stance": null,
    "HitLevel": [
      "M",
      "M",
      "M"
    ],
    "Impact": 21,
    "Damage": "16,10,21",
    "DamageDec": 47,
    "Block": "-12",
    "BlockDec": -12,
    "Hit": "4",
    "HitDec": 4,
    "CounterHit": "4",
    "CounterHitDec": 4,
    "GuardBurst": 10,
    "Notes": "NC. TJ. Forces crouch on hit. Have perfect input version"
  },
  {
    "ID": 3095,
    "stringCommand": ":B+K:",
    "Command": [
      "B+C"
    ],
    "Stance": [
      "WR"
    ],
    "HitLevel": [
      "M",
      "M"
    ],
    "Impact": 22,
    "Damage": "22,16",
    "DamageDec": 38,
    "Block": "-22",
    "BlockDec": -22,
    "Hit": "LNC",
    "HitDec": null,
    "CounterHit": "LNC",
    "CounterHitDec": null,
    "GuardBurst": 9,
    "Notes": ":SS: into LS. :LH: on throw whiff"
  },
  {
    "ID": 3096,
    "stringCommand": ":B+K:",
    "Command": [
      "B+C"
    ],
    "Stance": [
      "BT"
    ],
    "HitLevel": [
      "M"
    ],
    "Impact": 18,
    "Damage": "30",
    "DamageDec": 30,
    "Block": "-8",
    "BlockDec": -8,
    "Hit": "LNC",
    "HitDec": null,
    "CounterHit": "LNC",
    "CounterHitDec": null,
    "GuardBurst": 9,
    "Notes": null
  },
  {
    "ID": 3097,
    "stringCommand": ":A+G:",
    "Command": [
      "A+D"
    ],
    "Stance": null,
    "HitLevel": [
      "H"
    ],
    "Impact": 18,
    "Damage": "50",
    "DamageDec": 50,
    "Block": null,
    "BlockDec": null,
    "Hit": null,
    "HitDec": null,
    "CounterHit": null,
    "CounterHitDec": null,
    "GuardBurst": null,
    "Notes": ":TH:"
  },
  {
    "ID": 3098,
    "stringCommand": ":4::A+G:",
    "Command": [
      "4",
      "A+D"
    ],
    "Stance": null,
    "HitLevel": [
      "H"
    ],
    "Impact": 18,
    "Damage": "55",
    "DamageDec": 55,
    "Block": "8",
    "BlockDec": 8,
    "Hit": null,
    "HitDec": null,
    "CounterHit": null,
    "CounterHitDec": null,
    "GuardBurst": null,
    "Notes": ":TH:"
  },
  {
    "ID": 3099,
    "stringCommand": ":4::6::A+G:",
    "Command": [
      "4",
      "6",
      "A+D"
    ],
    "Stance": null,
    "HitLevel": [
      "H"
    ],
    "Impact": 18,
    "Damage": "0",
    "DamageDec": 0,
    "Block": "-4",
    "BlockDec": -4,
    "Hit": "10",
    "HitDec": 10,
    "CounterHit": null,
    "CounterHitDec": null,
    "GuardBurst": null,
    "Notes": ":TH:"
  },
  {
    "ID": 3100,
    "stringCommand": ":4::6::A+G::B:",
    "Command": [
      "4",
      "6",
      "A+D",
      "B"
    ],
    "Stance": null,
    "HitLevel": [
      "H"
    ],
    "Impact": 18,
    "Damage": "30",
    "DamageDec": 30,
    "Block": "-4",
    "BlockDec": -4,
    "Hit": "8",
    "HitDec": 8,
    "CounterHit": null,
    "CounterHitDec": null,
    "GuardBurst": null,
    "Notes": ":TH: NC. +8 when broken"
  },
  {
    "ID": 3101,
    "stringCommand": ":4::6::A+G::(B):",
    "Command": [
      "4",
      "6",
      "A+D",
      "(B)"
    ],
    "Stance": [
      "Short Hold"
    ],
    "HitLevel": [
      "H"
    ],
    "Impact": 18,
    "Damage": "42",
    "DamageDec": 42,
    "Block": "-4",
    "BlockDec": -4,
    "Hit": "KND",
    "HitDec": null,
    "CounterHit": "KND",
    "CounterHitDec": null,
    "GuardBurst": 20,
    "Notes": ":TH: Leaves at perfect tip range"
  },
  {
    "ID": 3102,
    "stringCommand": ":4::6::A+G::(B):",
    "Command": [
      "4",
      "6",
      "A+D",
      "(B)"
    ],
    "Stance": [
      "Full Hold"
    ],
    "HitLevel": [
      "H"
    ],
    "Impact": 18,
    "Damage": "42",
    "DamageDec": 42,
    "Block": "8",
    "BlockDec": 8,
    "Hit": "STN",
    "HitDec": null,
    "CounterHit": "STN",
    "CounterHitDec": null,
    "GuardBurst": 41,
    "Notes": ":TH: Leaves at perfect tip range"
  },
  {
    "ID": 3103,
    "stringCommand": ":A+G:",
    "Command": [
      "A+D"
    ],
    "Stance": [
      "Right Side"
    ],
    "HitLevel": [
      "H"
    ],
    "Impact": 18,
    "Damage": "64",
    "DamageDec": 64,
    "Block": null,
    "BlockDec": null,
    "Hit": null,
    "HitDec": null,
    "CounterHit": null,
    "CounterHitDec": null,
    "GuardBurst": null,
    "Notes": ":TH:"
  },
  {
    "ID": 3104,
    "stringCommand": ":A+G:",
    "Command": [
      "A+D"
    ],
    "Stance": [
      "Left Side"
    ],
    "HitLevel": [
      "H"
    ],
    "Impact": 18,
    "Damage": "60",
    "DamageDec": 60,
    "Block": null,
    "BlockDec": null,
    "Hit": null,
    "HitDec": null,
    "CounterHit": null,
    "CounterHitDec": null,
    "GuardBurst": null,
    "Notes": ":TH:"
  },
  {
    "ID": 3105,
    "stringCommand": ":A+G:",
    "Command": [
      "A+D"
    ],
    "Stance": [
      "Back Side"
    ],
    "HitLevel": [
      "H"
    ],
    "Impact": 18,
    "Damage": "72",
    "DamageDec": 72,
    "Block": null,
    "BlockDec": null,
    "Hit": null,
    "HitDec": null,
    "CounterHit": null,
    "CounterHitDec": null,
    "GuardBurst": null,
    "Notes": ":TH:"
  },
  {
    "ID": 3106,
    "stringCommand": ":(3):_:(6):_:(9)::A:",
    "Command": [
      "(3)",
      "_",
      "(6)",
      "_",
      "(9)",
      "A"
    ],
    "Stance": null,
    "HitLevel": [
      "M"
    ],
    "Impact": 18,
    "Damage": "20",
    "DamageDec": 20,
    "Block": "-8",
    "BlockDec": -8,
    "Hit": "2",
    "HitDec": 2,
    "CounterHit": "2",
    "CounterHitDec": 2,
    "GuardBurst": 1,
    "Notes": "TC[9-26]"
  },
  {
    "ID": 3107,
    "stringCommand": ":(2):_:(8)::A:",
    "Command": [
      "(2)",
      "_",
      "(8)",
      "A"
    ],
    "Stance": null,
    "HitLevel": [
      "M"
    ],
    "Impact": 22,
    "Damage": "15",
    "DamageDec": 15,
    "Block": "-16",
    "BlockDec": -16,
    "Hit": "-4",
    "HitDec": -4,
    "CounterHit": "-4",
    "CounterHitDec": -4,
    "GuardBurst": 1,
    "Notes": "TJ[30-47]"
  },
  {
    "ID": 3108,
    "stringCommand": ":(2):_:(8)::A::A:",
    "Command": [
      "(2)",
      "_",
      "(8)",
      "A",
      "A"
    ],
    "Stance": null,
    "HitLevel": [
      "M",
      "M"
    ],
    "Impact": 22,
    "Damage": "15,16",
    "DamageDec": 31,
    "Block": "-12",
    "BlockDec": -12,
    "Hit": "KND",
    "HitDec": null,
    "CounterHit": "KND",
    "CounterHitDec": null,
    "GuardBurst": 3,
    "Notes": "TJ[1-18]. TJ[41-53]. NCC"
  },
  {
    "ID": 3109,
    "stringCommand": ":(2):_:(8)::A:",
    "Command": [
      "(2)",
      "_",
      "(8)",
      "A"
    ],
    "Stance": [
      "tip range"
    ],
    "HitLevel": [
      "M"
    ],
    "Impact": 22,
    "Damage": "25",
    "DamageDec": 25,
    "Block": "-16",
    "BlockDec": -16,
    "Hit": "-4",
    "HitDec": -4,
    "CounterHit": "-4",
    "CounterHitDec": -4,
    "GuardBurst": 1,
    "Notes": "TJ[30-47]"
  },
  {
    "ID": 3110,
    "stringCommand": ":(2):_:(8)::A::A:",
    "Command": [
      "(2)",
      "_",
      "(8)",
      "A",
      "A"
    ],
    "Stance": [
      "tip range"
    ],
    "HitLevel": [
      "M",
      "M"
    ],
    "Impact": 22,
    "Damage": "25,3",
    "DamageDec": 28,
    "Block": "-12",
    "BlockDec": -12,
    "Hit": "KND",
    "HitDec": null,
    "CounterHit": "KND",
    "CounterHitDec": null,
    "GuardBurst": 3,
    "Notes": "TJ[1-18]. TJ[41-53]. NCC"
  },
  {
    "ID": 3111,
    "stringCommand": ":(1):_:(7)::A:",
    "Command": [
      "(1)",
      "_",
      "(7)",
      "A"
    ],
    "Stance": null,
    "HitLevel": [
      "L"
    ],
    "Impact": 28,
    "Damage": "15",
    "DamageDec": 15,
    "Block": "-14",
    "BlockDec": -14,
    "Hit": "0",
    "HitDec": 0,
    "CounterHit": "0",
    "CounterHitDec": 0,
    "GuardBurst": 4,
    "Notes": "TC[26-42]"
  },
  {
    "ID": 3112,
    "stringCommand": ":(1):_:(7)::A:",
    "Command": [
      "(1)",
      "_",
      "(7)",
      "A"
    ],
    "Stance": [
      "tip range"
    ],
    "HitLevel": [
      "L"
    ],
    "Impact": 28,
    "Damage": "25",
    "DamageDec": 25,
    "Block": "-8",
    "BlockDec": -8,
    "Hit": "KND",
    "HitDec": null,
    "CounterHit": "KND",
    "CounterHitDec": null,
    "GuardBurst": 4,
    "Notes": "TC[26-42]"
  },
  {
    "ID": 3113,
    "stringCommand": ":(4)::A:",
    "Command": [
      "(4)",
      "A"
    ],
    "Stance": null,
    "HitLevel": [
      "L"
    ],
    "Impact": 32,
    "Damage": "18",
    "DamageDec": 18,
    "Block": "-12",
    "BlockDec": -12,
    "Hit": "-2",
    "HitDec": -2,
    "CounterHit": "-2",
    "CounterHitDec": -2,
    "GuardBurst": 4,
    "Notes": null
  },
  {
    "ID": 3114,
    "stringCommand": ":(4)::A:",
    "Command": [
      "(4)",
      "A"
    ],
    "Stance": [
      "tip range"
    ],
    "HitLevel": [
      "L"
    ],
    "Impact": 32,
    "Damage": "33",
    "DamageDec": 33,
    "Block": "2",
    "BlockDec": 2,
    "Hit": "STN",
    "HitDec": null,
    "CounterHit": "STN",
    "CounterHitDec": null,
    "GuardBurst": 4,
    "Notes": ":LH: on tip range"
  },
  {
    "ID": 3115,
    "stringCommand": ":(3):_:(6):_:(9)::B:",
    "Command": [
      "(3)",
      "_",
      "(6)",
      "_",
      "(9)",
      "B"
    ],
    "Stance": null,
    "HitLevel": [
      "M"
    ],
    "Impact": 18,
    "Damage": "22",
    "DamageDec": 22,
    "Block": "-12",
    "BlockDec": -12,
    "Hit": "4",
    "HitDec": 4,
    "CounterHit": "4",
    "CounterHitDec": 4,
    "GuardBurst": 9,
    "Notes": null
  },
  {
    "ID": 3116,
    "stringCommand": ":(3):_:(6):_:(9)::(B):",
    "Command": [
      "(3)",
      "_",
      "(6)",
      "_",
      "(9)",
      "(B)"
    ],
    "Stance": null,
    "HitLevel": [
      "M"
    ],
    "Impact": 24,
    "Damage": "35",
    "DamageDec": 35,
    "Block": "-4",
    "BlockDec": -4,
    "Hit": "KND",
    "HitDec": null,
    "CounterHit": "KND",
    "CounterHitDec": null,
    "GuardBurst": 15,
    "Notes": "i22 at tip range"
  },
  {
    "ID": 3117,
    "stringCommand": ":(2):_:(8)::B:",
    "Command": [
      "(2)",
      "_",
      "(8)",
      "B"
    ],
    "Stance": null,
    "HitLevel": [
      "M"
    ],
    "Impact": 19,
    "Damage": "32",
    "DamageDec": 32,
    "Block": "-14",
    "BlockDec": -14,
    "Hit": "LNC",
    "HitDec": null,
    "CounterHit": "LNC",
    "CounterHitDec": null,
    "GuardBurst": 9,
    "Notes": "TC[10-15]"
  },
  {
    "ID": 3118,
    "stringCommand": ":(1):_:(7)::B:",
    "Command": [
      "(1)",
      "_",
      "(7)",
      "B"
    ],
    "Stance": null,
    "HitLevel": [
      "L"
    ],
    "Impact": 22,
    "Damage": "22",
    "DamageDec": 22,
    "Block": "-20",
    "BlockDec": -20,
    "Hit": "-8",
    "HitDec": -8,
    "CounterHit": "-8",
    "CounterHitDec": -8,
    "GuardBurst": 2,
    "Notes": "TC. Guard cancellable"
  },
  {
    "ID": 3119,
    "stringCommand": ":(1):_:(7)::B:",
    "Command": [
      "(1)",
      "_",
      "(7)",
      "B"
    ],
    "Stance": [
      "tip range"
    ],
    "HitLevel": [
      "L"
    ],
    "Impact": 22,
    "Damage": "34",
    "DamageDec": 34,
    "Block": "-10",
    "BlockDec": -10,
    "Hit": "KND",
    "HitDec": null,
    "CounterHit": "KND",
    "CounterHitDec": null,
    "GuardBurst": 2,
    "Notes": "TC. Guard cancellable"
  },
  {
    "ID": 3120,
    "stringCommand": ":(4)::B:",
    "Command": [
      "(4)",
      "B"
    ],
    "Stance": null,
    "HitLevel": [
      "M"
    ],
    "Impact": 34,
    "Damage": "20",
    "DamageDec": 20,
    "Block": "2",
    "BlockDec": 2,
    "Hit": "STN",
    "HitDec": null,
    "CounterHit": "STN",
    "CounterHitDec": null,
    "GuardBurst": 9,
    "Notes": "TC & TJ. Forces crouchon block"
  },
  {
    "ID": 3121,
    "stringCommand": ":(3):_:(6):_:(9)::K:",
    "Command": [
      "(3)",
      "_",
      "(6)",
      "_",
      "(9)",
      "C"
    ],
    "Stance": null,
    "HitLevel": [
      "M"
    ],
    "Impact": 22,
    "Damage": "10",
    "DamageDec": 10,
    "Block": "-10",
    "BlockDec": -10,
    "Hit": "2",
    "HitDec": 2,
    "CounterHit": "2",
    "CounterHitDec": 2,
    "GuardBurst": 2,
    "Notes": "TJ[5-16]"
  },
  {
    "ID": 3122,
    "stringCommand": ":(3):_:(6):_:(9)::K::K:",
    "Command": [
      "(3)",
      "_",
      "(6)",
      "_",
      "(9)",
      "C",
      "C"
    ],
    "Stance": null,
    "HitLevel": [
      "M",
      "M"
    ],
    "Impact": 22,
    "Damage": "10,1",
    "DamageDec": 11,
    "Block": "-14",
    "BlockDec": -14,
    "Hit": "-4",
    "HitDec": -4,
    "CounterHit": "-4",
    "CounterHitDec": -4,
    "GuardBurst": 4,
    "Notes": "NC. TJ[5-16]"
  },
  {
    "ID": 3123,
    "stringCommand": ":(3):_:(6):_:(9)::K::K::K:",
    "Command": [
      "(3)",
      "_",
      "(6)",
      "_",
      "(9)",
      "C",
      "C",
      "C"
    ],
    "Stance": null,
    "HitLevel": [
      "M",
      "M",
      "H"
    ],
    "Impact": 22,
    "Damage": "10,10,14",
    "DamageDec": 34,
    "Block": "-8",
    "BlockDec": -8,
    "Hit": "8",
    "HitDec": 8,
    "CounterHit": "18",
    "CounterHitDec": 18,
    "GuardBurst": 6,
    "Notes": "NCC. TJ[5-16]"
  },
  {
    "ID": 3124,
    "stringCommand": ":(2):_:(8)::K:",
    "Command": [
      "(2)",
      "_",
      "(8)",
      "C"
    ],
    "Stance": null,
    "HitLevel": [
      "M"
    ],
    "Impact": 30,
    "Damage": "30",
    "DamageDec": 30,
    "Block": "0",
    "BlockDec": 0,
    "Hit": "KND",
    "HitDec": null,
    "CounterHit": "KND",
    "CounterHitDec": null,
    "GuardBurst": 9,
    "Notes": "TJ. Forces crouch on block"
  },
  {
    "ID": 3125,
    "stringCommand": ":(1):_:(4):_:(7)::K:",
    "Command": [
      "(1)",
      "_",
      "(4)",
      "_",
      "(7)",
      "C"
    ],
    "Stance": null,
    "HitLevel": [
      "M"
    ],
    "Impact": 26,
    "Damage": "32",
    "DamageDec": 32,
    "Block": "-8",
    "BlockDec": -8,
    "Hit": "8",
    "HitDec": 8,
    "CounterHit": "8",
    "CounterHitDec": 8,
    "GuardBurst": 1,
    "Notes": "TJ. :LH: when countering low attack"
  },
  {
    "ID": 3126,
    "stringCommand": ":(3):_:(6):_:(9)::A+B:",
    "Command": [
      "(3)",
      "_",
      "(6)",
      "_",
      "(9)",
      "A+B"
    ],
    "Stance": null,
    "HitLevel": [
      "M"
    ],
    "Impact": 28,
    "Damage": "40",
    "DamageDec": 40,
    "Block": "-2",
    "BlockDec": -2,
    "Hit": "KND",
    "HitDec": null,
    "CounterHit": "KND",
    "CounterHitDec": null,
    "GuardBurst": 25,
    "Notes": null
  },
  {
    "ID": 3127,
    "stringCommand": ":(2):_:(8)::A+B:",
    "Command": [
      "(2)",
      "_",
      "(8)",
      "A+B"
    ],
    "Stance": null,
    "HitLevel": [
      "H"
    ],
    "Impact": 22,
    "Damage": "20",
    "DamageDec": 20,
    "Block": "-12",
    "BlockDec": -12,
    "Hit": "6",
    "HitDec": 6,
    "CounterHit": "6",
    "CounterHitDec": 6,
    "GuardBurst": 4,
    "Notes": null
  },
  {
    "ID": 3128,
    "stringCommand": ":(2):_:(8)::A+B::A:",
    "Command": [
      "(2)",
      "_",
      "(8)",
      "A+B",
      "A"
    ],
    "Stance": null,
    "HitLevel": [
      "H",
      "H"
    ],
    "Impact": 22,
    "Damage": "20,28",
    "DamageDec": 48,
    "Block": "-4",
    "BlockDec": -4,
    "Hit": "KND",
    "HitDec": null,
    "CounterHit": "KND",
    "CounterHitDec": null,
    "GuardBurst": 5,
    "Notes": "NC"
  },
  {
    "ID": 3129,
    "stringCommand": ":(1):_:(4):_:(7)::A+B:",
    "Command": [
      "(1)",
      "_",
      "(4)",
      "_",
      "(7)",
      "A+B"
    ],
    "Stance": null,
    "HitLevel": [
      "M"
    ],
    "Impact": 40,
    "Damage": "52",
    "DamageDec": 52,
    "Block": "-2",
    "BlockDec": -2,
    "Hit": "LNC",
    "HitDec": null,
    "CounterHit": "LNC",
    "CounterHitDec": null,
    "GuardBurst": 41,
    "Notes": "TJ. :LH: when guard bursts. Forces crouch on block."
  },
  {
    "ID": 3130,
    "stringCommand": ":(3):_:(6):_:(9)::B+K:",
    "Command": [
      "(3)",
      "_",
      "(6)",
      "_",
      "(9)",
      "B+C"
    ],
    "Stance": null,
    "HitLevel": [
      "M",
      "M"
    ],
    "Impact": 18,
    "Damage": "11,21",
    "DamageDec": 32,
    "Block": "-22",
    "BlockDec": -22,
    "Hit": "KND",
    "HitDec": null,
    "CounterHit": "KND",
    "CounterHitDec": null,
    "GuardBurst": 10,
    "Notes": "NCC. TC& TJ. Forces crouch on block."
  },
  {
    "ID": 3131,
    "stringCommand": ":(3):_:(6):_:(9)::(B)+(K):",
    "Command": [
      "(3)",
      "_",
      "(6)",
      "_",
      "(9)",
      "(B)+(C)"
    ],
    "Stance": null,
    "HitLevel": [
      "M",
      "M",
      "SL"
    ],
    "Impact": 24,
    "Damage": "16,26,5",
    "DamageDec": 47,
    "Block": "-6",
    "BlockDec": -6,
    "Hit": "0",
    "HitDec": 0,
    "CounterHit": "KND",
    "CounterHitDec": null,
    "GuardBurst": 17,
    "Notes": "TC & TJ"
  },
  {
    "ID": 3132,
    "stringCommand": ":(1):_:(4):_:(7)::B+K:",
    "Command": [
      "(1)",
      "_",
      "(4)",
      "_",
      "(7)",
      "B+C"
    ],
    "Stance": null,
    "HitLevel": [
      "M"
    ],
    "Impact": 38,
    "Damage": "40",
    "DamageDec": 40,
    "Block": "-6",
    "BlockDec": -6,
    "Hit": "KND",
    "HitDec": null,
    "CounterHit": "KND",
    "CounterHitDec": null,
    "GuardBurst": 12,
    "Notes": "TC[16-37]"
  },
  {
    "ID": 3133,
    "stringCommand": ":(1):_:(4):_:(7)::(B)+(K):",
    "Command": [
      "(1)",
      "_",
      "(4)",
      "_",
      "(7)",
      "(B)+(C)"
    ],
    "Stance": null,
    "HitLevel": [
      "M"
    ],
    "Impact": 52,
    "Damage": "44",
    "DamageDec": 44,
    "Block": "8",
    "BlockDec": 8,
    "Hit": "KND",
    "HitDec": null,
    "CounterHit": "KND",
    "CounterHitDec": null,
    "GuardBurst": 16,
    "Notes": ":BA:. TC[16-37]"
  },
  {
    "ID": 3134,
    "stringCommand": ":K:",
    "Command": [
      "C"
    ],
    "Stance": [
      "RUN"
    ],
    "HitLevel": [
      "L"
    ],
    "Impact": 20,
    "Damage": "26",
    "DamageDec": 26,
    "Block": "-22",
    "BlockDec": -22,
    "Hit": "KND",
    "HitDec": null,
    "CounterHit": "KND",
    "CounterHitDec": null,
    "GuardBurst": 9,
    "Notes": null
  },
  {
    "ID": 3135,
    "stringCommand": ":A:",
    "Command": [
      "A"
    ],
    "Stance": [
      "LS"
    ],
    "HitLevel": [
      "H"
    ],
    "Impact": 20,
    "Damage": "32",
    "DamageDec": 32,
    "Block": "-2",
    "BlockDec": -2,
    "Hit": "KND",
    "HitDec": null,
    "CounterHit": "KND",
    "CounterHitDec": null,
    "GuardBurst": 4,
    "Notes": "TC[8-15]. Exhibits tip range behaviour at all ranges"
  },
  {
    "ID": 3136,
    "stringCommand": ":B:",
    "Command": [
      "B"
    ],
    "Stance": [
      "LS"
    ],
    "HitLevel": [
      "L"
    ],
    "Impact": 22,
    "Damage": "34",
    "DamageDec": 34,
    "Block": "-10",
    "BlockDec": -10,
    "Hit": "KND",
    "HitDec": null,
    "CounterHit": "KND",
    "CounterHitDec": null,
    "GuardBurst": 9,
    "Notes": "TC[1-52]. Exhibits tip range behaviour at all ranges. Guard cancellable."
  },
  {
    "ID": 3137,
    "stringCommand": ":K:",
    "Command": [
      "C"
    ],
    "Stance": [
      "LS"
    ],
    "HitLevel": [
      "M"
    ],
    "Impact": 36,
    "Damage": "35",
    "DamageDec": 35,
    "Block": "6",
    "BlockDec": 6,
    "Hit": "KND",
    "HitDec": null,
    "CounterHit": "KND",
    "CounterHitDec": null,
    "GuardBurst": 12,
    "Notes": ":BA:. TJ"
  },
  {
    "ID": 3138,
    "stringCommand": ":B+G:",
    "Command": [
      "B+D"
    ],
    "Stance": null,
    "HitLevel": [
      "M"
    ],
    "Impact": 46,
    "Damage": "35",
    "DamageDec": 35,
    "Block": "-10",
    "BlockDec": -10,
    "Hit": null,
    "HitDec": null,
    "CounterHit": null,
    "CounterHitDec": null,
    "GuardBurst": 25,
    "Notes": ":RE:[6-30]"
  },
  {
    "ID": 3139,
    "stringCommand": ":(B)+(G):",
    "Command": [
      "(B)+(D)"
    ],
    "Stance": null,
    "HitLevel": [
      "M"
    ],
    "Impact": 66,
    "Damage": "45",
    "DamageDec": 45,
    "Block": "8",
    "BlockDec": 8,
    "Hit": null,
    "HitDec": null,
    "CounterHit": null,
    "CounterHitDec": null,
    "GuardBurst": 29,
    "Notes": ":RE:[6-50]"
  },
  {
    "ID": 3140,
    "stringCommand": ":A:",
    "Command": [
      "A"
    ],
    "Stance": [
      "RE"
    ],
    "HitLevel": null,
    "Impact": 36,
    "Damage": "18",
    "DamageDec": 18,
    "Block": "-4",
    "BlockDec": -4,
    "Hit": "8",
    "HitDec": 8,
    "CounterHit": "8",
    "CounterHitDec": 8,
    "GuardBurst": 33,
    "Notes": null
  },
  {
    "ID": 3141,
    "stringCommand": ":A::A:",
    "Command": [
      "A",
      "A"
    ],
    "Stance": [
      "RE"
    ],
    "HitLevel": null,
    "Impact": 36,
    "Damage": "18,25",
    "DamageDec": 43,
    "Block": "-12",
    "BlockDec": -12,
    "Hit": "KND",
    "HitDec": null,
    "CounterHit": "KND",
    "CounterHitDec": null,
    "GuardBurst": 33,
    "Notes": null
  },
  {
    "ID": 3142,
    "stringCommand": ":A::B:",
    "Command": [
      "A",
      "B"
    ],
    "Stance": [
      "RE"
    ],
    "HitLevel": null,
    "Impact": 36,
    "Damage": "18,23",
    "DamageDec": 41,
    "Block": "-4",
    "BlockDec": -4,
    "Hit": "KND",
    "HitDec": null,
    "CounterHit": "KND",
    "CounterHitDec": null,
    "GuardBurst": 44,
    "Notes": null
  },
  {
    "ID": 3143,
    "stringCommand": ":A::(B):",
    "Command": [
      "A",
      "(B)"
    ],
    "Stance": [
      "RE"
    ],
    "HitLevel": null,
    "Impact": 36,
    "Damage": "18,35",
    "DamageDec": 53,
    "Block": "0",
    "BlockDec": 0,
    "Hit": "LNC",
    "HitDec": null,
    "CounterHit": "LNC",
    "CounterHitDec": null,
    "GuardBurst": 50,
    "Notes": null
  },
  {
    "ID": 3144,
    "stringCommand": ":A:",
    "Command": [
      "A"
    ],
    "Stance": [
      "RE2"
    ],
    "HitLevel": null,
    "Impact": 36,
    "Damage": "23",
    "DamageDec": 23,
    "Block": "-4",
    "BlockDec": -4,
    "Hit": "STN",
    "HitDec": null,
    "CounterHit": "STN",
    "CounterHitDec": null,
    "GuardBurst": 33,
    "Notes": null
  },
  {
    "ID": 3145,
    "stringCommand": ":A::A:",
    "Command": [
      "A",
      "A"
    ],
    "Stance": [
      "RE2"
    ],
    "HitLevel": null,
    "Impact": 36,
    "Damage": "23,25",
    "DamageDec": 48,
    "Block": "-12",
    "BlockDec": -12,
    "Hit": "KND",
    "HitDec": null,
    "CounterHit": "KND",
    "CounterHitDec": null,
    "GuardBurst": 33,
    "Notes": null
  },
  {
    "ID": 3146,
    "stringCommand": ":A::B:",
    "Command": [
      "A",
      "B"
    ],
    "Stance": [
      "RE2"
    ],
    "HitLevel": null,
    "Impact": 36,
    "Damage": "23,23",
    "DamageDec": 46,
    "Block": "-4",
    "BlockDec": -4,
    "Hit": "KND",
    "HitDec": null,
    "CounterHit": "KND",
    "CounterHitDec": null,
    "GuardBurst": 44,
    "Notes": null
  },
  {
    "ID": 3147,
    "stringCommand": ":A::(B):",
    "Command": [
      "A",
      "(B)"
    ],
    "Stance": [
      "RE2"
    ],
    "HitLevel": null,
    "Impact": 36,
    "Damage": "23,29",
    "DamageDec": 52,
    "Block": "0",
    "BlockDec": 0,
    "Hit": "LNC",
    "HitDec": null,
    "CounterHit": "LNC",
    "CounterHitDec": null,
    "GuardBurst": 50,
    "Notes": null
  },
  {
    "ID": 3148,
    "stringCommand": ":B:",
    "Command": [
      "B"
    ],
    "Stance": [
      "RE"
    ],
    "HitLevel": null,
    "Impact": 34,
    "Damage": "30",
    "DamageDec": 30,
    "Block": null,
    "BlockDec": null,
    "Hit": "LNC",
    "HitDec": null,
    "CounterHit": "LNC",
    "CounterHitDec": null,
    "GuardBurst": 50,
    "Notes": null
  },
  {
    "ID": 3149,
    "stringCommand": ":B:",
    "Command": [
      "B"
    ],
    "Stance": [
      "RE2"
    ],
    "HitLevel": null,
    "Impact": 34,
    "Damage": "39",
    "DamageDec": 39,
    "Block": null,
    "BlockDec": null,
    "Hit": "LNC",
    "HitDec": null,
    "CounterHit": "LNC",
    "CounterHitDec": null,
    "GuardBurst": 50,
    "Notes": null
  },
  {
    "ID": 3150,
    "stringCommand": ":K:",
    "Command": [
      "C"
    ],
    "Stance": [
      "RE"
    ],
    "HitLevel": null,
    "Impact": 48,
    "Damage": "30",
    "DamageDec": 30,
    "Block": "12",
    "BlockDec": 12,
    "Hit": "KND",
    "HitDec": null,
    "CounterHit": "KND",
    "CounterHitDec": null,
    "GuardBurst": 33,
    "Notes": null
  },
  {
    "ID": 3151,
    "stringCommand": ":K:",
    "Command": [
      "C"
    ],
    "Stance": [
      "RE2"
    ],
    "HitLevel": null,
    "Impact": 48,
    "Damage": "39",
    "DamageDec": 39,
    "Block": "12",
    "BlockDec": 12,
    "Hit": "KND",
    "HitDec": null,
    "CounterHit": "KND",
    "CounterHitDec": null,
    "GuardBurst": 33,
    "Notes": null
  },
  {
    "ID": 3152,
    "stringCommand": ":A+B+K:",
    "Command": [
      "A+B+C"
    ],
    "Stance": null,
    "HitLevel": [
      "M"
    ],
    "Impact": 18,
    "Damage": "80",
    "DamageDec": 80,
    "Block": "-16",
    "BlockDec": -16,
    "Hit": "KND",
    "HitDec": null,
    "CounterHit": "KND",
    "CounterHitDec": null,
    "GuardBurst": 10,
    "Notes": ":CE:"
  },
  {
    "ID": 3153,
    "stringCommand": ":4::A+B+K:",
    "Command": [
      "4",
      "A+B+C"
    ],
    "Stance": null,
    "HitLevel": [
      "SM"
    ],
    "Impact": 6,
    "Damage": "0",
    "DamageDec": 0,
    "Block": "0",
    "BlockDec": 0,
    "Hit": "8",
    "HitDec": 8,
    "CounterHit": "8",
    "CounterHitDec": 8,
    "GuardBurst": 0,
    "Notes": "invincible since i4. Pushback happens at i6"
  },
  {
    "ID": 3154,
    "stringCommand": ":2::3::6::A+B+K:",
    "Command": [
      "2",
      "3",
      "6",
      "A+B+C"
    ],
    "Stance": null,
    "HitLevel": [
      "SL",
      "SL",
      "SL",
      "M"
    ],
    "Impact": 16,
    "Damage": "13,4,4,20",
    "DamageDec": 41,
    "Block": "-2",
    "BlockDec": -2,
    "Hit": "4",
    "HitDec": 4,
    "CounterHit": "4",
    "CounterHitDec": 4,
    "GuardBurst": 12,
    "Notes": null
  },
  {
    "ID": 3155,
    "stringCommand": ":2::3::6::(A)+(B)+(K):",
    "Command": [
      "2",
      "3",
      "6",
      "(A)+(B)+(C)"
    ],
    "Stance": null,
    "HitLevel": [
      "SL",
      "SL",
      "SL",
      "M"
    ],
    "Impact": 24,
    "Damage": "18,4,4,23",
    "DamageDec": 49,
    "Block": "4",
    "BlockDec": 4,
    "Hit": "10",
    "HitDec": 10,
    "CounterHit": "10",
    "CounterHitDec": 10,
    "GuardBurst": 20,
    "Notes": null
  },
  {
    "ID": 3156,
    "stringCommand": ":6::A:",
    "Command": [
      "6",
      "A"
    ],
    "Stance": [
      "SC"
    ],
    "HitLevel": [
      "H"
    ],
    "Impact": 20,
    "Damage": "39",
    "DamageDec": 39,
    "Block": "2",
    "BlockDec": 2,
    "Hit": "KND",
    "HitDec": null,
    "CounterHit": "KND",
    "CounterHitDec": null,
    "GuardBurst": 9,
    "Notes": ":BA:. :LH: on long range running counter"
  },
  {
    "ID": 3157,
    "stringCommand": ":B::B::B:",
    "Command": [
      "B",
      "B",
      "B"
    ],
    "Stance": [
      "SC"
    ],
    "HitLevel": [
      "M",
      "M",
      "M"
    ],
    "Impact": 20,
    "Damage": "15,13,30",
    "DamageDec": 58,
    "Block": "4",
    "BlockDec": 4,
    "Hit": "KND",
    "HitDec": null,
    "CounterHit": "KND",
    "CounterHitDec": null,
    "GuardBurst": 15,
    "Notes": ":BA:"
  },
  {
    "ID": 3158,
    "stringCommand": ":1::B:",
    "Command": [
      "1",
      "B"
    ],
    "Stance": [
      "SC"
    ],
    "HitLevel": [
      "L"
    ],
    "Impact": 22,
    "Damage": "44",
    "DamageDec": 44,
    "Block": "2",
    "BlockDec": 2,
    "Hit": "KND",
    "HitDec": null,
    "CounterHit": "KND",
    "CounterHitDec": null,
    "GuardBurst": 15,
    "Notes": ":BA:"
  },
  {
    "ID": 3159,
    "stringCommand": ":1::K::K:",
    "Command": [
      "1",
      "C",
      "C"
    ],
    "Stance": [
      "SC",
      "FC"
    ],
    "HitLevel": [
      "L",
      "M"
    ],
    "Impact": 22,
    "Damage": "16,19,19",
    "DamageDec": 54,
    "Block": "-14",
    "BlockDec": -14,
    "Hit": "KND",
    "HitDec": null,
    "CounterHit": "KND",
    "CounterHitDec": null,
    "GuardBurst": 7,
    "Notes": "NC. :SS: into LS"
  },
  {
    "ID": 3160,
    "stringCommand": ":1::K::K::B:",
    "Command": [
      "1",
      "C",
      "C",
      "B"
    ],
    "Stance": [
      "SC",
      "FC"
    ],
    "HitLevel": [
      "L",
      "M",
      "M"
    ],
    "Impact": 22,
    "Damage": "16,19,19,14",
    "DamageDec": 68,
    "Block": "-12",
    "BlockDec": -12,
    "Hit": "KND",
    "HitDec": null,
    "CounterHit": "KND",
    "CounterHitDec": null,
    "GuardBurst": 12,
    "Notes": "NC"
  },
  {
    "ID": 3161,
    "stringCommand": ":(3):_:(6):_:(9)::A::A:",
    "Command": [
      "(3)",
      "_",
      "(6)",
      "_",
      "(9)",
      "A",
      "A"
    ],
    "Stance": [
      "SC"
    ],
    "HitLevel": [
      "M",
      "H",
      "H"
    ],
    "Impact": 18,
    "Damage": "22,11,25",
    "DamageDec": 58,
    "Block": "-6",
    "BlockDec": -6,
    "Hit": "KND",
    "HitDec": null,
    "CounterHit": "KND",
    "CounterHitDec": null,
    "GuardBurst": 5,
    "Notes": "NC"
  },
  {
    "ID": 3162,
    "stringCommand": ":(2):_:(8)::A::A::A:",
    "Command": [
      "(2)",
      "_",
      "(8)",
      "A",
      "A",
      "A"
    ],
    "Stance": [
      "SC"
    ],
    "HitLevel": [
      "M",
      "M",
      "M"
    ],
    "Impact": 22,
    "Damage": "16,17,19",
    "DamageDec": 52,
    "Block": "-12",
    "BlockDec": -12,
    "Hit": "5",
    "HitDec": 5,
    "CounterHit": "5",
    "CounterHitDec": 5,
    "GuardBurst": 5,
    "Notes": "NCC. 2nd and 3rd hit are NC"
  },
  {
    "ID": 3163,
    "stringCommand": ":(2):_:(8)::A::A::A::A:",
    "Command": [
      "(2)",
      "_",
      "(8)",
      "A",
      "A",
      "A",
      "A"
    ],
    "Stance": [
      "SC"
    ],
    "HitLevel": [
      "M",
      "M",
      "M",
      "M"
    ],
    "Impact": 22,
    "Damage": "16,17,19,14",
    "DamageDec": 66,
    "Block": "-12",
    "BlockDec": -12,
    "Hit": "KND",
    "HitDec": null,
    "CounterHit": "KND",
    "CounterHitDec": null,
    "GuardBurst": 6,
    "Notes": "NCC"
  },
  {
    "ID": 3164,
    "stringCommand": ":(1):_:(7)::B:",
    "Command": [
      "(1)",
      "_",
      "(7)",
      "B"
    ],
    "Stance": [
      "SC"
    ],
    "HitLevel": [
      "L"
    ],
    "Impact": 22,
    "Damage": "44",
    "DamageDec": 44,
    "Block": "2",
    "BlockDec": 2,
    "Hit": "KND",
    "HitDec": null,
    "CounterHit": "KND",
    "CounterHitDec": null,
    "GuardBurst": 15,
    "Notes": ":BA:. TC"
  },
  {
    "ID": 3165,
    "stringCommand": ":(3):_:(6):_:(9)::A+B:",
    "Command": [
      "(3)",
      "_",
      "(6)",
      "_",
      "(9)",
      "A+B"
    ],
    "Stance": [
      "SC"
    ],
    "HitLevel": [
      "M"
    ],
    "Impact": 28,
    "Damage": "55",
    "DamageDec": 55,
    "Block": "2",
    "BlockDec": 2,
    "Hit": "KND",
    "HitDec": null,
    "CounterHit": "KND",
    "CounterHitDec": null,
    "GuardBurst": 25,
    "Notes": ":BA:"
  },
  {
    "ID": 3166,
    "stringCommand": ":(1):_:(4):_:(7)::A+B:",
    "Command": [
      "(1)",
      "_",
      "(4)",
      "_",
      "(7)",
      "A+B"
    ],
    "Stance": [
      "SC"
    ],
    "HitLevel": [
      "M"
    ],
    "Impact": 40,
    "Damage": "57",
    "DamageDec": 57,
    "Block": "6",
    "BlockDec": 6,
    "Hit": "LNC",
    "HitDec": null,
    "CounterHit": "LNC",
    "CounterHitDec": null,
    "GuardBurst": 41,
    "Notes": ":BA:. TJ. :LH: on guard burst"
  },
  {
    "ID": 3167,
    "stringCommand": ":(1):_:(4):_:(7)::B+K:",
    "Command": [
      "(1)",
      "_",
      "(4)",
      "_",
      "(7)",
      "B+C"
    ],
    "Stance": [
      "SC"
    ],
    "HitLevel": [
      "M"
    ],
    "Impact": 38,
    "Damage": "48",
    "DamageDec": 48,
    "Block": "8",
    "BlockDec": 8,
    "Hit": "KND",
    "HitDec": null,
    "CounterHit": "KND",
    "CounterHitDec": null,
    "GuardBurst": 16,
    "Notes": ":BA:"
  },
  {
    "ID": 3168,
    "stringCommand": ":(1):_:(4):_:(7)::(B)+(K):",
    "Command": [
      "(1)",
      "_",
      "(4)",
      "_",
      "(7)",
      "(B)+(C)"
    ],
    "Stance": [
      "SC"
    ],
    "HitLevel": [
      "M"
    ],
    "Impact": 52,
    "Damage": "57",
    "DamageDec": 57,
    "Block": "UB",
    "BlockDec": null,
    "Hit": "KND",
    "HitDec": null,
    "CounterHit": "KND",
    "CounterHitDec": null,
    "GuardBurst": null,
    "Notes": ":UA:. Guard cancel :SS: into LS"
  }
]